{
    "id":"001",
    "createDate":"2016/9/1",
    "startDate":"2016/9/1",
    "closeDate":"2016/9/30",
    "status":"open",
    "rideEvent":{
        "project":"SV71"
    },
    "person":{
        "name":"hupei"
    },
    "vehicle":{
        "name":"G10"
    },
    "results":[{
               "rank":5.5,
               "evaluateItem":{
               
               },
               "issues":[{
                         "issue":""}
                         ]},
               {
               "rank":7.5,
               "evaluateItem":{
               
               },
               "issues":[{
                         "issue":""}
                         ]}
               ]
}